{
    "path_src": "/opt/cresi/cresi",
    "path_data_root": "/opt/cresi/data",
    "path_results_root": "/opt/cresi/results",
    "speed_conversion_file": "/opt/cresi/cresi/configs/speed_conversion_binned7.csv",
    "save_weights_dir": "/opt/cresi/cresi/configs/weights",
    "raw_data_dir": "raw_data",
    "eight_bit_dir": "/opt/cresi/data/8bit_data",
    "sliced_dir": "/opt/cresi/data/sliced_data",
    "stitched_dir_raw": "stitched/mask_raw",
    "stitched_dir_count": "stitched/mask_count",
    "stitched_dir_norm": "stitched/mask_norm",
    "wkt_submission": "wkt_submission_nospeed.csv",
    "folds_file_name": "folds4.csv",
    "folds_save_dir": "folds",
    "tile_df_csv": "tile_df.csv",
    "merged_dir": "merged",
    "skeleton_dir": "skeleton",
    "skeleton_pkl_dir": "skel_nw_g",
    "geo_output_dir": "geo_files",
    "graph_dir": "graphs",
    "slice_x": 1300,
    "slice_y": 1300,
    "stride_x": 1280,
    "stride_y": 1280,
    "skeleton_thresh": 0.25,
    "min_spur_length_m": 12,
    "rdp_epsilon": 1,
    "num_folds": 1,
    "GSD": 0.4,
    "default_val_perc": 0.2,
    "num_channels": 3,
    "num_classes": 8,
    "skeleton_band": 7,
    "padding": 22,
    "iter_size": 1,
    "test_pad": 64,
    "predict_batch_size": 1,
    "target_cols": 1344,
    "target_rows": 1344,
    "ignore_target_size": false
}